[{
  "_id": {
    "$oid": "68fe41f10a10b16fbb5f57f0"
  },
  "bookKey": "/works/OL149867W",
  "text": "This was a beautiful read with strong characters.",
  "userName": "Ana",
  "userId": "ana456",
  "lastModified": {
    "$date": "2025-10-26T15:44:49.651Z"
  }
},
{
  "_id": {
    "$oid": "68fe420c0a10b16fbb5f57f1"
  },
  "bookKey": "/works/OL15437W",
  "text": "Loved the pacing and the philosophy.",
  "userName": "Valeria",
  "userId": "vvh123",
  "lastModified": {
    "$date": "2025-10-26T15:45:16.459Z"
  }
},
{
  "_id": {
    "$oid": "6917e4eb7742330f4d87c022"
  },
  "bookKey": "OL149867W",
  "text": "This book changed my life!",
  "userName": "Valeria",
  "userId": "vvh123",
  "lastModified": {
    "$date": "2025-11-15T02:26:51.620Z"
  }
},
{
  "_id": {
    "$oid": "6917e58e7742330f4d87c023"
  },
  "bookKey": "/works/OL149867W",
  "text": "This book left me with no words",
  "userName": "Valeria",
  "userId": "vvh123",
  "lastModified": {
    "$date": "2025-11-15T02:29:34.803Z"
  }
},
{
  "_id": {
    "$oid": "6936349765d0c06d2c971559"
  },
  "bookKey": "68d09245645ba8e7da63881b",
  "text": "I'm obsessed with this book!!",
  "userName": "Caleb",
  "userId": "Caleb234",
  "lastModified": {
    "$date": "2025-12-08T03:02:25.590Z"
  }
},
{
  "_id": {
    "$oid": "693648b0c81c4be418045171"
  },
  "bookKey": "/works/OL149869W",
  "text": "amazing book!!",
  "userName": "Caleb",
  "userId": "Caleb234",
  "lastModified": {
    "$date": "2025-12-08T03:40:42.386Z"
  }
},
{
  "_id": {
    "$oid": "693648e4c81c4be418045172"
  },
  "bookKey": "/works/OL26916W",
  "text": "I recommend this book %100!",
  "userName": "Caleb",
  "userId": "Caleb234",
  "lastModified": {
    "$date": "2025-12-08T03:41:24.870Z"
  }
},
{
  "_id": {
    "$oid": "69364975c81c4be418045173"
  },
  "bookKey": "/works/OL149869W",
  "text": "So surprised by the ending",
  "userName": "Chris",
  "userId": "Chris878",
  "lastModified": {
    "$date": "2025-12-08T03:43:49.568Z"
  }
},
{
  "_id": {
    "$oid": "6936499ac81c4be418045174"
  },
  "bookKey": "/works/OL21036W",
  "text": "Kate Chopin is the best!",
  "userName": "Chris",
  "userId": "Chris878",
  "lastModified": {
    "$date": "2025-12-08T03:44:26.470Z"
  }
},
{
  "_id": {
    "$oid": "693649cdc81c4be418045175"
  },
  "bookKey": "/works/OL45579W",
  "text": "Read it in less than a week. Love this book!",
  "userName": "Chris",
  "userId": "Chris878",
  "lastModified": {
    "$date": "2025-12-08T03:45:31.337Z"
  }
}]